pysequansutils/__init__.py
pysequansutils/atdriver.py
pysequansutils/caba.py
pysequansutils/cli_nvm_main.py
pysequansutils/cli_pysequans.py
pysequansutils/cli_upgrade_main.py
pysequansutils/codec.py
pysequansutils/crc.py
pysequansutils/firmwareinterface.py
pysequansutils/logfilters.py
pysequansutils/logging.yaml
pysequansutils/nvmstorage.py
pysequansutils/pysequans_errors.py
pysequansutils/signing.py
pysequansutils/status_codes.py
pysequansutils/stp.py
pysequansutils/upgrade.py
pysequansutils/fw/GM02RB6Q_LR8.0.5.13-59577.dup
pysequansutils-2.3.3.21.dist-info/LICENSE.txt
pysequansutils-2.3.3.21.dist-info/LICENSE_SEQUANS.txt
pysequansutils-2.3.3.21.dist-info/METADATA
pysequansutils-2.3.3.21.dist-info/WHEEL
pysequansutils-2.3.3.21.dist-info/entry_points.txt
pysequansutils-2.3.3.21.dist-info/top_level.txt
pysequansutils-2.3.3.21.dist-info/RECORD
